comdinheiro/__init__.py
comdinheiro/instruments.py
comdinheiro-0.1.6.dist-info/LICENSE
comdinheiro-0.1.6.dist-info/METADATA
comdinheiro-0.1.6.dist-info/WHEEL
comdinheiro-0.1.6.dist-info/top_level.txt
comdinheiro-0.1.6.dist-info/RECORD
